langchain_iointelligence/__init__.py
langchain_iointelligence/chat.py
langchain_iointelligence/exceptions.py
langchain_iointelligence/http_client.py
langchain_iointelligence/llm.py
langchain_iointelligence/streaming.py
langchain_iointelligence/utils.py
langchain_iointelligence-0.2.0.dist-info/licenses/LICENSE
langchain_iointelligence-0.2.0.dist-info/METADATA
langchain_iointelligence-0.2.0.dist-info/WHEEL
langchain_iointelligence-0.2.0.dist-info/top_level.txt
langchain_iointelligence-0.2.0.dist-info/RECORD
