Metadata-Version: 2.4
Name: langchain-iointelligence
Version: 0.2.0
Summary: LangChain integration for io Intelligence LLM API with OpenAI compatibility
Home-page: https://github.com/soh7410/langchain-iointelligence
Author: SOH
Author-email: io Intelligence <support@intelligence.io>
License: MIT
Project-URL: Homepage, https://github.com/soh7410/langchain-iointelligence
Project-URL: Repository, https://github.com/soh7410/langchain-iointelligence
Project-URL: Documentation, https://github.com/soh7410/langchain-iointelligence#readme
Project-URL: Bug Tracker, https://github.com/soh7410/langchain-iointelligence/issues
Keywords: langchain,llm,ai,openai,chat,language-model,io-intelligence
Classifier: Development Status :: 4 - Beta
Classifier: Intended Audience :: Developers
Classifier: License :: OSI Approved :: MIT License
Classifier: Operating System :: OS Independent
Classifier: Programming Language :: Python :: 3
Classifier: Programming Language :: Python :: 3.8
Classifier: Programming Language :: Python :: 3.9
Classifier: Programming Language :: Python :: 3.10
Classifier: Programming Language :: Python :: 3.11
Classifier: Programming Language :: Python :: 3.12
Classifier: Topic :: Scientific/Engineering :: Artificial Intelligence
Classifier: Topic :: Software Development :: Libraries :: Python Modules
Requires-Python: >=3.8
License-File: LICENSE
Requires-Dist: langchain-core>=0.1.0
Requires-Dist: requests>=2.25.0
Requires-Dist: python-dotenv>=0.19.0
Provides-Extra: dev
Requires-Dist: pytest>=7.0.0; extra == "dev"
Requires-Dist: pytest-cov>=4.0.0; extra == "dev"
Requires-Dist: flake8>=5.0.0; extra == "dev"
Requires-Dist: black>=22.0.0; extra == "dev"
Requires-Dist: isort>=5.10.0; extra == "dev"
Requires-Dist: mypy>=0.991; extra == "dev"
Dynamic: author
Dynamic: home-page
Dynamic: license-file
Dynamic: requires-python
